[
  {
    "name": "MeChat Chat App (ongoing)",
    "year": "2024",
    "liveDemoLink": null,
    "githubLink": "https://github.com/haidanglevn/mechat-frontend",
    "description": "A full-stack, real-time chat application built using React and .NET Core. The goal of this project is to implement state-of-the-art features similar to those found in modern chat applications. Key functionalities include SignalR for real-time notifications, a typing indicator to show when users are typing, encrypted messages for enhanced security, and more.",
    "techStack": [
      {
        "name": "React",
        "icon": "/assets/icons/react.png"
      },
      {
        "name": ".Net Core",
        "icon": "/assets/icons/netcore.png"
      },
      {
        "name": "PostgreSQL",
        "icon": "/assets/icons/postgresql.png"
      },
      {
        "name": "Typescript",
        "icon": "/assets/icons/typescript.png"
      },
      {
        "name": "Material UI",
        "icon": "/assets/icons/mui.png"
      }
    ],
    "images": [
      {
        "src": "/assets/mechat/mechat1.png",
        "title": "User Interface"
      }
    ]
  },
  {
    "name": "EcomEcho e-commerce platform",
    "year": "2023",
    "liveDemoLink": "https://ecomecho.netlify.app/",
    "githubLink": "https://github.com/haidanglevn/fs16_Frontend-project",
    "description": "EcomEcho is a fullstack project built at Integrify. The frontend website provides an user-friendly interface for users to browse the products, add them to cart then create orders, while Admin user can easily manage the data on the database. The backend server provides data on API request, contains business logics and stored product + user data onto the database. It serves API endpoints protected by role-based authorization, which ensures secure storage and data access only for the right users.",
    "techStack": [
      {
        "name": "React",
        "icon": "/assets/icons/react.png"
      },
      {
        "name": ".Net Core",
        "icon": "/assets/icons/netcore.png"
      },
      {
        "name": "PostgreSQL",
        "icon": "/assets/icons/postgresql.png"
      },
      {
        "name": "Typescript",
        "icon": "/assets/icons/typescript.png"
      },
      {
        "name": "Azure",
        "icon": "/assets/icons/azure.png"
      },
      {
        "name": "Material UI",
        "icon": "/assets/icons/mui.png"
      }
    ],
    "images": [
      {
        "src": "/assets/ecomecho/ecomecho1.png",
        "title": "Home page"
      },
      {
        "src": "/assets/ecomecho/ecomecho2.png",
        "title": "Product Page"
      },
      {
        "src": "/assets/ecomecho/ecomecho3.png",
        "title": "Cart Page"
      },
      {
        "src": "/assets/ecomecho/ecomecho4.png",
        "title": "Admin User Panel"
      },
      {
        "src": "/assets/ecomecho/ecomecho5.png",
        "title": "Create new product function"
      }
    ]
  },
  {
    "name": "Colleague Feedback System for Exove",
    "year": "2023",
    "liveDemoLink": null,
    "githubLink": "https://github.com/Colleague-Feedback-Team-1/colleague-feedback-frontend",
    "description": "A fullstack app made in collaboration with Exove to create a solution for the company's colleague feedback process. Its main goals is to replace current process of gathering feedback with GG Form, storing result in GG Sheets with an automated system with user-friendly UI and a database to store feedback data.",
    "techStack": [
      {
        "name": "React",
        "icon": "/assets/icons/react.png"
      },
      {
        "name": "NodeJS",
        "icon": "/assets/icons/nodejs.png"
      },
      {
        "name": "MongoDB",
        "icon": "/assets/icons/mongodb.png"
      },
      {
        "name": "Typescript",
        "icon": "/assets/icons/typescript.png"
      },
      {
        "name": "Material UI",
        "icon": "/assets/icons/mui.png"
      }
    ],
    "images": [
      {
        "src": "/assets/exove/exove1.png",
        "title": "User Dashboard"
      },
      {
        "src": "/assets/exove/exove2.png",
        "title": "Admin Dashboard"
      },
      {
        "src": "/assets/exove/exove3.png",
        "title": "Notification"
      },
      {
        "src": "/assets/exove/exove4.png",
        "title": "Feedback form"
      },
      {
        "src": "/assets/exove/exove5.png",
        "title": "Personal Performance Chart"
      }
    ]
  },
  {
    "name": "SkillsBridge landing page for TUTORS Oy",
    "year": "2023",
    "liveDemoLink": "https://www.skillsbridge.eu/",
    "githubLink": null,
    "description": "A front-end focused project that my team built during the internship with Tutors Oy. The page introduces SkillsBridge, an educational project funded by Erasmus+ that aims to research and build a platform to teach and learn game development. The page provides general information and encourage visitors to fill the research form to help the project. I contributed as both UX/UI Designer and FrontEnd Developer for the team.",
    "techStack": [
      {
        "name": "React",
        "icon": "/assets/icons/react.png"
      },
      {
        "name": "Figma",
        "icon": "/assets/icons/figma.png"
      }
    ],
    "images": [
      {
        "src": "/assets/skillsbridge/skillsbridge1.png",
        "title": "Hero & About Section"
      },
      {
        "src": "/assets/skillsbridge/skillsbridge2.png",
        "title": "Path, Support and Footer section"
      }
    ]
  },
  {
    "name": "Travel Planner App",
    "year": "2022",
    "liveDemoLink": "https://delightful-sherbet-1b7473.netlify.app/",
    "githubLink": "https://github.com/haidanglevn/BCH_Team5_TravelPlanner",
    "description": "A mobile travel planner webapp made as a team project in Helsinki Business College. The app ultilizes the Google Firebase to store data and manage login, together with OpenWeatherAPI and MapBoxAPI for location and weather data. Users can browse famous local attractions and plan their next trip with the built-in planner.",
    "techStack": [
      {
        "name": "React",
        "icon": "/assets/icons/react.png"
      },
      {
        "name": "Firebase",
        "icon": "/assets/icons/firebase.png"
      }
    ],
    "images": [
      {
        "src": "/assets/travelplanner/travelplanner1.png",
        "title": "Create a trip page"
      },
      {
        "src": "/assets/travelplanner/travelplanner2.png",
        "title": "Home page"
      }
    ]
  }
]
